nc_py_frm/__init__.py
nc_py_frm/__main__.py
nc_py_frm/_version.py
nc_py_frm-0.0.1.dist-info/LICENSE
nc_py_frm-0.0.1.dist-info/METADATA
nc_py_frm-0.0.1.dist-info/WHEEL
nc_py_frm-0.0.1.dist-info/top_level.txt
nc_py_frm-0.0.1.dist-info/zip-safe
nc_py_frm-0.0.1.dist-info/RECORD
